justbe_webview/__init__.py
justbe_webview/py.typed
justbe_webview/schemas.py
justbe_webview-0.0.4.dist-info/METADATA
justbe_webview-0.0.4.dist-info/WHEEL
justbe_webview-0.0.4.dist-info/RECORD
