Metadata-Version: 2.4
Name: justbe-webview
Version: 0.0.4
Summary: A simple webview client
Requires-Python: >=3.12
Requires-Dist: aiofiles>=24.1.0
Requires-Dist: httpx>=0.27.2
Requires-Dist: msgspec>=0.19.0
Requires-Dist: pyee>=12.0.0
Requires-Dist: python-ulid>=3.0.0
Requires-Dist: types-aiofiles>=24.1.0.20240626
